equoai/__init__.py
equoai/main.py
equoai-1.0.5.dist-info/METADATA
equoai-1.0.5.dist-info/WHEEL
equoai-1.0.5.dist-info/top_level.txt
equoai-1.0.5.dist-info/RECORD
