Metadata-Version: 2.1
Name: equoai
Version: 1.0.5
Summary: Python client for accessing the EquoAI platform and all its core services
Download-URL: https://github.com/DavidHostler/equoai-client
Author: David Hostler
Requires-Dist: requests
Requires-Dist: numpy
Requires-Dist: tiktoken
